{"coleccion_VA": [{"Id":"0","Codpais":"VA","Pais":"VATICANO","Anho":"1961","Estatus":"1","Motivo":"Ostiense Basilica","Tmc":"","Subtema":""},{"Id":"1","Codpais":"VA","Pais":"VATICANO","Anho":"1963","Estatus":"1","Motivo":"St. Methodios","Tmc":"","Subtema":""},{"Id":"2","Codpais":"VA","Pais":"VATICANO","Anho":"1963","Estatus":"1","Motivo":"Nativity by Andea Bukuru","Tmc":"","Subtema":""},{"Id":"3","Codpais":"VA","Pais":"VATICANO","Anho":"1964","Estatus":"1","Motivo":"La Piedad de Miguelangel. Participation of Vatican at Universal Exhibition, New York","Tmc":"","Subtema":""},{"Id":"4","Codpais":"VA","Pais":"VATICANO","Anho":"1964","Estatus":"1","Motivo":"La Piedad de Miguelangel. Participation of Vatican at Universal Exhibition, New York","Tmc":"","Subtema":""},{"Id":"5","Codpais":"VA","Pais":"VATICANO","Anho":"1964","Estatus":"1","Motivo":"Michelangelo (1475-1564)","Tmc":"Gente","Subtema":"Arte"},{"Id":"6","Codpais":"VA","Pais":"VATICANO","Anho":"1964","Estatus":"1","Motivo":"16 Pro Isaías","Tmc":"ARTE","Subtema":""},{"Id":"7","Codpais":"VA","Pais":"VATICANO","Anho":"1964","Estatus":"1","Motivo":"12 Sib Sibila Délfica","Tmc":"ARTE","Subtema":""},{"Id":"8","Codpais":"VA","Pais":"VATICANO","Anho":"1964","Estatus":"1","Motivo":"17 Pro Jeremías","Tmc":"ARTE","Subtema":""},{"Id":"9","Codpais":"VA","Pais":"VATICANO","Anho":"1964","Estatus":"1","Motivo":"19 Pro Joel","Tmc":"ARTE","Subtema":""},{"Id":"10","Codpais":"VA","Pais":"VATICANO","Anho":"1965","Estatus":"1","Motivo":"Visita de Pablo VI a la ONU","Tmc":"","Subtema":""},{"Id":"11","Codpais":"VA","Pais":"VATICANO","Anho":"1966","Estatus":"1","Motivo":"Science","Tmc":"","Subtema":""},{"Id":"12","Codpais":"VA","Pais":"VATICANO","Anho":"1966","Estatus":"1","Motivo":"Iron art","Tmc":"","Subtema":""},{"Id":"13","Codpais":"VA","Pais":"VATICANO","Anho":"1967","Estatus":"1","Motivo":"Altar de San Pedro y Baldaquino ","Tmc":"","Subtema":""},{"Id":"14","Codpais":"VA","Pais":"VATICANO","Anho":"1972","Estatus":"1","Motivo":"St. John, Apocalypse","Tmc":"","Subtema":""},{"Id":"15","Codpais":"VA","Pais":"VATICANO","Anho":"1973","Estatus":"1","Motivo":"La Piedad de Miguelangel  ","Tmc":"","Subtema":""},{"Id":"16","Codpais":"VA","Pais":"VATICANO","Anho":"1976","Estatus":"1","Motivo":"Fountain of the Sacrament","Tmc":"","Subtema":""},{"Id":"17","Codpais":"VA","Pais":"VATICANO","Anho":"1977","Estatus":"1","Motivo":"La dormición de la Virgen","Tmc":"","Subtema":""},{"Id":"18","Codpais":"VA","Pais":"VATICANO","Anho":"1979","Estatus":"1","Motivo":"San Estanislao","Tmc":"","Subtema":""},{"Id":"19","Codpais":"VA","Pais":"VATICANO","Anho":"1980","Estatus":"1","Motivo":"Nursia, St. Benedictus v.","Tmc":"","Subtema":""},{"Id":"20","Codpais":"VA","Pais":"VATICANO","Anho":"1980","Estatus":"1","Motivo":"The Royal Staircase","Tmc":"","Subtema":""},{"Id":"21","Codpais":"VA","Pais":"VATICANO","Anho":"1982","Estatus":"1","Motivo":"Robbia, Lucca della","Tmc":"","Subtema":""},{"Id":"22","Codpais":"VA","Pais":"VATICANO","Anho":"1982","Estatus":"1","Motivo":"Monument to Gregory XIII","Tmc":"","Subtema":""},{"Id":"23","Codpais":"VA","Pais":"VATICANO","Anho":"1982","Estatus":"1","Motivo":"Monument to Gregory XIII","Tmc":"","Subtema":""},{"Id":"24","Codpais":"VA","Pais":"VATICANO","Anho":"1984","Estatus":"1","Motivo":"St. Casimir","Tmc":"","Subtema":""},{"Id":"25","Codpais":"VA","Pais":"VATICANO","Anho":"1984","Estatus":"1","Motivo":"Vatican Observatory","Tmc":"","Subtema":""},{"Id":"26","Codpais":"VA","Pais":"VATICANO","Anho":"1986","Estatus":"1","Motivo":"Patrons sick people and hospitals","Tmc":"","Subtema":""},{"Id":"27","Codpais":"VA","Pais":"VATICANO","Anho":"1988","Estatus":"1","Motivo":"Veronese, Paolo","Tmc":"","Subtema":""},{"Id":"28","Codpais":"VA","Pais":"VATICANO","Anho":"1988","Estatus":"1","Motivo":"Scenes from the Bible","Tmc":"","Subtema":""},{"Id":"29","Codpais":"VA","Pais":"VATICANO","Anho":"1990","Estatus":"1","Motivo":"S. Mainardi, Holy Child --Ghirlandaio?","Tmc":"ARTE","Subtema":"Pintura"},{"Id":"30","Codpais":"VA","Pais":"VATICANO","Anho":"1991","Estatus":"1","Motivo":"44 Eleazar - Mathan","Tmc":"ARTE","Subtema":""},{"Id":"31","Codpais":"VA","Pais":"VATICANO","Anho":"1991","Estatus":"0","Motivo":"45 Eleazar - Mathan","Tmc":"ARTE","Subtema":"Capilla Sixtina"},{"Id":"32","Codpais":"VA","Pais":"VATICANO","Anho":"1991","Estatus":"1","Motivo":"42 Iacob","Tmc":"ARTE","Subtema":""},{"Id":"33","Codpais":"VA","Pais":"VATICANO","Anho":"1991","Estatus":"0","Motivo":"43 Ioseph","Tmc":"ARTE","Subtema":"Capilla Sixtina"},{"Id":"34","Codpais":"VA","Pais":"VATICANO","Anho":"1991","Estatus":"0","Motivo":"Josías, Jeconías y Salatiel","Tmc":"ARTE","Subtema":"Capilla Sixtina"},{"Id":"35","Codpais":"VA","Pais":"VATICANO","Anho":"1991","Estatus":"0","Motivo":"Josías, Jeconías y Salatiel","Tmc":"ARTE","Subtema":"Capilla Sixtina"},{"Id":"36","Codpais":"VA","Pais":"VATICANO","Anho":"1991","Estatus":"0","Motivo":"Asa - Iosaphat - Ioram","Tmc":"ARTE","Subtema":"Capilla Sixtina"},{"Id":"37","Codpais":"VA","Pais":"VATICANO","Anho":"1991","Estatus":"1","Motivo":"Asa - Iosaphat - Ioram","Tmc":"ARTE","Subtema":""},{"Id":"38","Codpais":"VA","Pais":"VATICANO","Anho":"1991","Estatus":"0","Motivo":"Zorobabel - Abiud - Eliachim","Tmc":"ARTE","Subtema":"Capilla Sixtina"},{"Id":"39","Codpais":"VA","Pais":"VATICANO","Anho":"1991","Estatus":"0","Motivo":"Zorobabel - Abiud - Eliachim","Tmc":"ARTE","Subtema":"Capilla Sixtina"},{"Id":"40","Codpais":"VA","Pais":"VATICANO","Anho":"1991","Estatus":"0","Motivo":"Azor - Sadoch","Tmc":"ARTE","Subtema":"Capilla Sixtina"},{"Id":"41","Codpais":"VA","Pais":"VATICANO","Anho":"1991","Estatus":"0","Motivo":"Azor - Sadoch","Tmc":"ARTE","Subtema":"Capilla Sixtina"},{"Id":"42","Codpais":"VA","Pais":"VATICANO","Anho":"1991","Estatus":"1","Motivo":"Saint Brigid and Mary","Tmc":"","Subtema":""},{"Id":"43","Codpais":"VA","Pais":"VATICANO","Anho":"1992","Estatus":"1","Motivo":"St. Joseph Cottolengo and the Virgin","Tmc":"","Subtema":""},{"Id":"44","Codpais":"VA","Pais":"VATICANO","Anho":"1993","Estatus":"1","Motivo":"Hands hold out the bread","Tmc":"","Subtema":""},{"Id":"45","Codpais":"VA","Pais":"VATICANO","Anho":"1993","Estatus":"1","Motivo":"World Journeys Pope Johannes Paulus II","Tmc":"","Subtema":""},{"Id":"46","Codpais":"VA","Pais":"VATICANO","Anho":"1993","Estatus":"1","Motivo":"Madonna of Solothurn, detail","Tmc":"","Subtema":""},{"Id":"47","Codpais":"VA","Pais":"VATICANO","Anho":"1993","Estatus":"0","Motivo":"450th anniversary of the death of Hans Holbein the Younger (1497-1543)","Tmc":"Gente","Subtema":"Pintor"},{"Id":"48","Codpais":"VA","Pais":"VATICANO","Anho":"1994","Estatus":"1","Motivo":"World Journeys Pope Johannes Paulus II","Tmc":"","Subtema":""},{"Id":"49","Codpais":"VA","Pais":"VATICANO","Anho":"1994","Estatus":"1","Motivo":"La Santa Familia","Tmc":"","Subtema":""},{"Id":"50","Codpais":"VA","Pais":"VATICANO","Anho":"1995","Estatus":"1","Motivo":"Transport Casa Sancta to Loreto","Tmc":"","Subtema":""},{"Id":"51","Codpais":"VA","Pais":"VATICANO","Anho":"1995","Estatus":"1","Motivo":"Transport Casa Sancta to Loreto","Tmc":"","Subtema":""},{"Id":"52","Codpais":"VA","Pais":"VATICANO","Anho":"1995","Estatus":"1","Motivo":"Fountain Rhyncospermum","Tmc":"","Subtema":""},{"Id":"53","Codpais":"VA","Pais":"VATICANO","Anho":"1995","Estatus":"1","Motivo":"Rose Avenue, the Palazzo Barberini","Tmc":"","Subtema":""},{"Id":"54","Codpais":"VA","Pais":"VATICANO","Anho":"1995","Estatus":"1","Motivo":"Statue of Apollo Citaredo","Tmc":"","Subtema":""},{"Id":"55","Codpais":"VA","Pais":"VATICANO","Anho":"1995","Estatus":"1","Motivo":"U.N.O.","Tmc":"","Subtema":""},{"Id":"56","Codpais":"VA","Pais":"VATICANO","Anho":"1996","Estatus":"1","Motivo":"Return Marco Polo from China","Tmc":"","Subtema":""},{"Id":"57","Codpais":"VA","Pais":"VATICANO","Anho":"1996","Estatus":"1","Motivo":"Las tentaciones de Jesús","Tmc":"","Subtema":""},{"Id":"58","Codpais":"VA","Pais":"VATICANO","Anho":"1996","Estatus":"1","Motivo":"World journeys Pope Johannes Paulus II","Tmc":"","Subtema":""},{"Id":"59","Codpais":"VA","Pais":"VATICANO","Anho":"1996","Estatus":"1","Motivo":"World journeys Pope Johannes Paulus II","Tmc":"","Subtema":""},{"Id":"60","Codpais":"VA","Pais":"VATICANO","Anho":"1997","Estatus":"1","Motivo":"Vehículos del Papa. Carroza da viaggio","Tmc":"","Subtema":""},{"Id":"61","Codpais":"VA","Pais":"VATICANO","Anho":"1997","Estatus":"1","Motivo":"Vehículos del Papa","Tmc":"","Subtema":""},{"Id":"62","Codpais":"VA","Pais":"VATICANO","Anho":"1997","Estatus":"1","Motivo":"Vehículos del Papa","Tmc":"","Subtema":""},{"Id":"63","Codpais":"VA","Pais":"VATICANO","Anho":"1997","Estatus":"1","Motivo":"Vehículos del Papa","Tmc":"","Subtema":""},{"Id":"64","Codpais":"VA","Pais":"VATICANO","Anho":"1997","Estatus":"1","Motivo":"Vehículos del Papa","Tmc":"","Subtema":""},{"Id":"65","Codpais":"VA","Pais":"VATICANO","Anho":"1997","Estatus":"1","Motivo":"Chalice, consecrated wafer and coat of arms Wroclaw","Tmc":"","Subtema":""},{"Id":"66","Codpais":"VA","Pais":"VATICANO","Anho":"1997","Estatus":"1","Motivo":"La tempestad calmada. Miniatura códice","Tmc":"","Subtema":""},{"Id":"67","Codpais":"VA","Pais":"VATICANO","Anho":"1997","Estatus":"1","Motivo":"Victems of earthquake","Tmc":"","Subtema":""},{"Id":"68","Codpais":"VA","Pais":"VATICANO","Anho":"1997","Estatus":"1","Motivo":"Victems of earthquake","Tmc":"","Subtema":""},{"Id":"69","Codpais":"VA","Pais":"VATICANO","Anho":"1997","Estatus":"1","Motivo":"Victems of earthquake","Tmc":"","Subtema":""},{"Id":"70","Codpais":"VA","Pais":"VATICANO","Anho":"1998","Estatus":"1","Motivo":"Papas. Bonifacio VIII","Tmc":"","Subtema":""},{"Id":"71","Codpais":"VA","Pais":"VATICANO","Anho":"1998","Estatus":"1","Motivo":"Ángeles","Tmc":"","Subtema":""},{"Id":"72","Codpais":"VA","Pais":"VATICANO","Anho":"1998","Estatus":"1","Motivo":"Ángeles","Tmc":"","Subtema":""},{"Id":"73","Codpais":"VA","Pais":"VATICANO","Anho":"1999","Estatus":"1","Motivo":"Monte Tabor (Palestina)","Tmc":"","Subtema":""},{"Id":"74","Codpais":"VA","Pais":"VATICANO","Anho":"1999","Estatus":"1","Motivo":"Balloons, lens and the map of Europe","Tmc":"","Subtema":""},{"Id":"75","Codpais":"VA","Pais":"VATICANO","Anho":"1999","Estatus":"1","Motivo":"Annunciation and Angelo","Tmc":"","Subtema":""},{"Id":"76","Codpais":"VA","Pais":"VATICANO","Anho":"1999","Estatus":"1","Motivo":"Baptism of Jesus","Tmc":"","Subtema":""},{"Id":"77","Codpais":"VA","Pais":"VATICANO","Anho":"2000","Estatus":"1","Motivo":"Basílica de San Pedro","Tmc":"","Subtema":""},{"Id":"78","Codpais":"VA","Pais":"VATICANO","Anho":"2000","Estatus":"1","Motivo":"Santa María la Mayor","Tmc":"","Subtema":""},{"Id":"79","Codpais":"VA","Pais":"VATICANO","Anho":"2000","Estatus":"1","Motivo":"Juan Pablo II y la Juventud","Tmc":"","Subtema":""},{"Id":"80","Codpais":"VA","Pais":"VATICANO","Anho":"2000","Estatus":"1","Motivo":"Navidad. Giotto. Nacimiento","Tmc":"ARTE","Subtema":"Pintura"},{"Id":"81","Codpais":"VA","Pais":"VATICANO","Anho":"2000","Estatus":"1","Motivo":"Navidad. Giotto. Detalle del Nacimiento,  Niño Jesús","Tmc":"ARTE","Subtema":"Pintura"},{"Id":"82","Codpais":"VA","Pais":"VATICANO","Anho":"2000","Estatus":"0","Motivo":"Navidad. Giotto. Detalle del Nacimiento,  la Virgen María","Tmc":"","Subtema":""},{"Id":"83","Codpais":"VA","Pais":"VATICANO","Anho":"2000","Estatus":"0","Motivo":"Navidad. Giotto. Detalle del Nacimiento,  San José","Tmc":"","Subtema":""},{"Id":"84","Codpais":"VA","Pais":"VATICANO","Anho":"2001","Estatus":"1","Motivo":"Capilla Sixtina","Tmc":"","Subtema":""},{"Id":"85","Codpais":"VA","Pais":"VATICANO","Anho":"2001","Estatus":"1","Motivo":"Capilla Sixtina","Tmc":"","Subtema":""},{"Id":"86","Codpais":"VA","Pais":"VATICANO","Anho":"2001","Estatus":"1","Motivo":"Giusappe Verdi","Tmc":"","Subtema":""},{"Id":"87","Codpais":"VA","Pais":"VATICANO","Anho":"2001","Estatus":"1","Motivo":"Drawing of young Slovenian","Tmc":"","Subtema":""},{"Id":"88","Codpais":"VA","Pais":"VATICANO","Anho":"2001","Estatus":"1","Motivo":"World Journeys Pope Paulus II+J45800","Tmc":"","Subtema":""},{"Id":"89","Codpais":"VA","Pais":"VATICANO","Anho":"2001","Estatus":"1","Motivo":"Feed the hungry","Tmc":"","Subtema":""},{"Id":"90","Codpais":"VA","Pais":"VATICANO","Anho":"2001","Estatus":"1","Motivo":"Comfort the afflicted","Tmc":"","Subtema":""},{"Id":"91","Codpais":"VA","Pais":"VATICANO","Anho":"2001","Estatus":"1","Motivo":"Clothe the naked","Tmc":"","Subtema":""},{"Id":"92","Codpais":"VA","Pais":"VATICANO","Anho":"2001","Estatus":"1","Motivo":"Head of Medusa","Tmc":"","Subtema":""},{"Id":"93","Codpais":"VA","Pais":"VATICANO","Anho":"2002","Estatus":"1","Motivo":"Institute Giuseppe","Tmc":"","Subtema":""},{"Id":"94","Codpais":"VA","Pais":"VATICANO","Anho":"2002","Estatus":"1","Motivo":"Our Lady of the rejected","Tmc":"","Subtema":""},{"Id":"95","Codpais":"VA","Pais":"VATICANO","Anho":"2002","Estatus":"1","Motivo":"Our Lady of Help","Tmc":"","Subtema":""},{"Id":"96","Codpais":"VA","Pais":"VATICANO","Anho":"2002","Estatus":"1","Motivo":"Virgin of Deisis","Tmc":"","Subtema":""},{"Id":"97","Codpais":"VA","Pais":"VATICANO","Anho":"2002","Estatus":"1","Motivo":"Via Appia and stamp 1 scudo of the Papal States","Tmc":"","Subtema":""},{"Id":"98","Codpais":"VA","Pais":"VATICANO","Anho":"2002","Estatus":"1","Motivo":"Walls of the Vatican stamp and 10 c. Papal State","Tmc":"","Subtema":""},{"Id":"99","Codpais":"VA","Pais":"VATICANO","Anho":"2002","Estatus":"1","Motivo":"La última cena","Tmc":"","Subtema":""},{"Id":"100","Codpais":"VA","Pais":"VATICANO","Anho":"2003","Estatus":"1","Motivo":"St. Stephen's, preaches to the people","Tmc":"","Subtema":""},{"Id":"101","Codpais":"VA","Pais":"VATICANO","Anho":"2003","Estatus":"1","Motivo":"The Judgement of St. Lawrence","Tmc":"","Subtema":""},{"Id":"102","Codpais":"VA","Pais":"VATICANO","Anho":"2003","Estatus":"1","Motivo":"Piedad. Van Gogh","Tmc":"ARTE","Subtema":"Pintura"},{"Id":"103","Codpais":"VA","Pais":"VATICANO","Anho":"2003","Estatus":"1","Motivo":"Portrait of Josemaria Escriva and rose","Tmc":"","Subtema":""},{"Id":"104","Codpais":"VA","Pais":"VATICANO","Anho":"2004","Estatus":"1","Motivo":"Juan Pablo II. Bosnia and Herzegovina","Tmc":"","Subtema":""},{"Id":"105","Codpais":"VA","Pais":"VATICANO","Anho":"2004","Estatus":"1","Motivo":"Juan Pablo II. Croacia","Tmc":"","Subtema":""},{"Id":"106","Codpais":"VA","Pais":"VATICANO","Anho":"2004","Estatus":"1","Motivo":"Juan Pablo II","Tmc":"","Subtema":""},{"Id":"107","Codpais":"VA","Pais":"VATICANO","Anho":"2004","Estatus":"1","Motivo":"Irlanda","Tmc":"","Subtema":""},{"Id":"108","Codpais":"VA","Pais":"VATICANO","Anho":"2004","Estatus":"1","Motivo":"Italia","Tmc":"","Subtema":""},{"Id":"109","Codpais":"VA","Pais":"VATICANO","Anho":"2004","Estatus":"1","Motivo":"San Marino","Tmc":"","Subtema":""},{"Id":"110","Codpais":"VA","Pais":"VATICANO","Anho":"2004","Estatus":"1","Motivo":"España","Tmc":"","Subtema":""},{"Id":"111","Codpais":"VA","Pais":"VATICANO","Anho":"2004","Estatus":"1","Motivo":"Consecration of the bread","Tmc":"","Subtema":""},{"Id":"112","Codpais":"VA","Pais":"VATICANO","Anho":"2004","Estatus":"1","Motivo":"Francesco Petrarca","Tmc":"","Subtema":""},{"Id":"113","Codpais":"VA","Pais":"VATICANO","Anho":"2005","Estatus":"1","Motivo":"Pen and coats of arms","Tmc":"","Subtema":""},{"Id":"114","Codpais":"VA","Pais":"VATICANO","Anho":"2005","Estatus":"1","Motivo":"Detail of the altarpiece of the Resurrection by Perugino","Tmc":"","Subtema":""},{"Id":"115","Codpais":"VA","Pais":"VATICANO","Anho":"2005","Estatus":"1","Motivo":"Detail of the altarpiece of the Resurrection by Perugino","Tmc":"","Subtema":""},{"Id":"116","Codpais":"VA","Pais":"VATICANO","Anho":"2005","Estatus":"1","Motivo":"Plate depicting some fish, the work of Picasso","Tmc":"","Subtema":""},{"Id":"117","Codpais":"VA","Pais":"VATICANO","Anho":"2005","Estatus":"1","Motivo":"Portrait of Benedict XVI, Habemus Papam","Tmc":"","Subtema":""},{"Id":"118","Codpais":"VA","Pais":"VATICANO","Anho":"2005","Estatus":"1","Motivo":"Portrait of Benedict XVI, tu es Petrus","Tmc":"","Subtema":""},{"Id":"119","Codpais":"VA","Pais":"VATICANO","Anho":"2005","Estatus":"1","Motivo":"Juan Pablo II. Berna","Tmc":"","Subtema":""},{"Id":"120","Codpais":"VA","Pais":"VATICANO","Anho":"2006","Estatus":"1","Motivo":"Hands clasped in prayer, church, mosque and synagogue","Tmc":"","Subtema":""},{"Id":"121","Codpais":"VA","Pais":"VATICANO","Anho":"2006","Estatus":"1","Motivo":"San Francisco Javier","Tmc":"","Subtema":""},{"Id":"122","Codpais":"VA","Pais":"VATICANO","Anho":"2006","Estatus":"1","Motivo":"Madonna and Child by Mantegna","Tmc":"","Subtema":""},{"Id":"123","Codpais":"VA","Pais":"VATICANO","Anho":"2006","Estatus":"1","Motivo":"Benedicto XVI. Bari","Tmc":"","Subtema":""},{"Id":"124","Codpais":"VA","Pais":"VATICANO","Anho":"2006","Estatus":"1","Motivo":"Colonia. Benedicto XVI","Tmc":"","Subtema":""},{"Id":"125","Codpais":"VA","Pais":"VATICANO","Anho":"2006","Estatus":"1","Motivo":"Child in the desert","Tmc":"","Subtema":""},{"Id":"126","Codpais":"VA","Pais":"VATICANO","Anho":"2006","Estatus":"1","Motivo":"Child and herd","Tmc":"","Subtema":""},{"Id":"127","Codpais":"VA","Pais":"VATICANO","Anho":"2006","Estatus":"1","Motivo":"Laoconte","Tmc":"","Subtema":""},{"Id":"128","Codpais":"VA","Pais":"VATICANO","Anho":"2006","Estatus":"1","Motivo":"Hijo de Laoconte","Tmc":"","Subtema":""},{"Id":"129","Codpais":"VA","Pais":"VATICANO","Anho":"2006","Estatus":"1","Motivo":"Navidad. Shepherds, by Silvio Consadori","Tmc":"","Subtema":""},{"Id":"130","Codpais":"VA","Pais":"VATICANO","Anho":"2007","Estatus":"1","Motivo":"Sculpture of St. Francis of Paola","Tmc":"","Subtema":""},{"Id":"131","Codpais":"VA","Pais":"VATICANO","Anho":"2007","Estatus":"1","Motivo":"Lamp and bulb","Tmc":"","Subtema":""},{"Id":"132","Codpais":"VA","Pais":"VATICANO","Anho":"2007","Estatus":"1","Motivo":"Monedas vaticanas","Tmc":"","Subtema":""},{"Id":"133","Codpais":"VA","Pais":"VATICANO","Anho":"2007","Estatus":"1","Motivo":"Stained glass window depicting St. Elizabeth","Tmc":"","Subtema":""},{"Id":"134","Codpais":"VA","Pais":"VATICANO","Anho":"2007","Estatus":"1","Motivo":"Turkey","Tmc":"","Subtema":""},{"Id":"135","Codpais":"VA","Pais":"VATICANO","Anho":"2007","Estatus":"1","Motivo":"Navidad. Nativity by Giuseppe Cali","Tmc":"","Subtema":""},{"Id":"136","Codpais":"VA","Pais":"VATICANO","Anho":"2008","Estatus":"1","Motivo":"10 Sib Sibila Libia","Tmc":"ARTE","Subtema":""},{"Id":"137","Codpais":"VA","Pais":"VATICANO","Anho":"2008","Estatus":"1","Motivo":"14 Sib Sibila Eritrea","Tmc":"ARTE","Subtema":""},{"Id":"138","Codpais":"VA","Pais":"VATICANO","Anho":"2008","Estatus":"1","Motivo":"12 Sib Sibila Délfica","Tmc":"ARTE","Subtema":""},{"Id":"139","Codpais":"VA","Pais":"VATICANO","Anho":"2008","Estatus":"0","Motivo":"11 Sib Sibila Cumana","Tmc":"ARTE","Subtema":"Capilla Sixtina"},{"Id":"140","Codpais":"VA","Pais":"VATICANO","Anho":"2008","Estatus":"1","Motivo":"15 Pro Daniel","Tmc":"ARTE","Subtema":""},{"Id":"141","Codpais":"VA","Pais":"VATICANO","Anho":"2008","Estatus":"1","Motivo":"40 Prophet Jonah","Tmc":"ARTE","Subtema":""},{"Id":"142","Codpais":"VA","Pais":"VATICANO","Anho":"2008","Estatus":"0","Motivo":"18 Pro Prophet Ezekiel","Tmc":"ARTE","Subtema":"Capilla Sixtina"},{"Id":"143","Codpais":"VA","Pais":"VATICANO","Anho":"2008","Estatus":"1","Motivo":"18 pro Zacarías","Tmc":"ARTE","Subtema":""},{"Id":"144","Codpais":"VA","Pais":"VATICANO","Anho":"2009","Estatus":"1","Motivo":"Astronomía","Tmc":"","Subtema":""},{"Id":"145","Codpais":"VA","Pais":"VATICANO","Anho":"2009","Estatus":"1","Motivo":"G.F.Händel","Tmc":"","Subtema":""},{"Id":"146","Codpais":"VA","Pais":"VATICANO","Anho":"2010","Estatus":"1","Motivo":"Portrait of Leo XIII","Tmc":"","Subtema":""},{"Id":"147","Codpais":"VA","Pais":"VATICANO","Anho":"2010","Estatus":"1","Motivo":"Cameroon and Angola","Tmc":"","Subtema":""},{"Id":"148","Codpais":"VA","Pais":"VATICANO","Anho":"2011","Estatus":"1","Motivo":"Pope Jean Paul II","Tmc":"","Subtema":""},{"Id":"149","Codpais":"VA","Pais":"VATICANO","Anho":"2011","Estatus":"1","Motivo":"Logo World Youth Day - Madrid","Tmc":"","Subtema":""},{"Id":"150","Codpais":"VA","Pais":"VATICANO","Anho":"2015","Estatus":"1","Motivo":"Pope Francis with baby","Tmc":"","Subtema":""},{"Id":"151","Codpais":"VA","Pais":"VATICANO","Anho":"2015","Estatus":"1","Motivo":"Pope Francis sentado","Tmc":"","Subtema":""},{"Id":"152","Codpais":"VA","Pais":"VATICANO","Anho":"2017","Estatus":"1","Motivo":"Pontificate of Pope Francis MMXVII","Tmc":"","Subtema":""},{"Id":"153","Codpais":"VA","Pais":"VATICANO","Anho":"1968","Estatus":"1","Motivo":"Arcangel San Gabriel","Tmc":"","Subtema":""},{"Id":"154","Codpais":"VA","Pais":"VATICANO","Anho":"1980","Estatus":"1","Motivo":"World journeys Pope Johannes Paulus II","Tmc":"","Subtema":""},{"Id":"155","Codpais":"VA","Pais":"VATICANO","Anho":"1988","Estatus":"1","Motivo":"World journeys Pope Johannes Paulus II","Tmc":"","Subtema":""},{"Id":"156","Codpais":"VA","Pais":"VATICANO","Anho":"2006","Estatus":"1","Motivo":"Navidad. Holy Family, by Silvio Consadori","Tmc":"","Subtema":""},{"Id":"157","Codpais":"VA","Pais":"VATICANO","Anho":"2013","Estatus":"1","Motivo":"Madonna del Giglio","Tmc":"","Subtema":""},{"Id":"158","Codpais":"VA","Pais":"VATICANO","Anho":"2013","Estatus":"1","Motivo":"Portrait of Pope Francis","Tmc":"","Subtema":""},{"Id":"159","Codpais":"VA","Pais":"VATICANO","Anho":"2013","Estatus":"1","Motivo":"Portrait of Pope Francis","Tmc":"","Subtema":""},{"Id":"160","Codpais":"VA","Pais":"VATICANO","Anho":"2014","Estatus":"1","Motivo":"Pascua MMXIV","Tmc":"","Subtema":""},{"Id":"161","Codpais":"VA","Pais":"VATICANO","Anho":"2015","Estatus":"1","Motivo":"Papa Francisco sentado, Fondo negro","Tmc":"","Subtema":""},{"Id":"162","Codpais":"VA","Pais":"VATICANO","Anho":"2018","Estatus":"0","Motivo":"","Tmc":"","Subtema":""},{"Id":"163","Codpais":"VA","Pais":"VATICANO","Anho":"2018","Estatus":"1","Motivo":"Sexto año del Pontificado del Papa Francisco","Tmc":"","Subtema":""},{"Id":"164","Codpais":"VA","Pais":"VATICANO","Anho":"2018","Estatus":"0","Motivo":"","Tmc":"","Subtema":""},{"Id":"165","Codpais":"VA","Pais":"VATICANO","Anho":"2018","Estatus":"0","Motivo":"","Tmc":"","Subtema":""},{"Id":"166","Codpais":"VA","Pais":"VATICANO","Anho":"2018","Estatus":"0","Motivo":"","Tmc":"","Subtema":""},{"Id":"167","Codpais":"VA","Pais":"VATICANO","Anho":"2018","Estatus":"0","Motivo":"","Tmc":"","Subtema":""},{"Id":"168","Codpais":"VA","Pais":"VATICANO","Anho":"2018","Estatus":"0","Motivo":"","Tmc":"","Subtema":""},{"Id":"169","Codpais":"VA","Pais":"VATICANO","Anho":"2018","Estatus":"0","Motivo":"","Tmc":"","Subtema":""},{"Id":"170","Codpais":"VA","Pais":"VATICANO","Anho":"2018","Estatus":"0","Motivo":"","Tmc":"","Subtema":""},{"Id":"171","Codpais":"VA","Pais":"VATICANO","Anho":"2018","Estatus":"0","Motivo":"","Tmc":"","Subtema":""},{"Id":"172","Codpais":"VA","Pais":"VATICANO","Anho":"2018","Estatus":"0","Motivo":"","Tmc":"","Subtema":""},{"Id":"173","Codpais":"VA","Pais":"VATICANO","Anho":"2018","Estatus":"0","Motivo":"","Tmc":"","Subtema":""},{"Id":"174","Codpais":"VA","Pais":"VATICANO","Anho":"2018","Estatus":"0","Motivo":"","Tmc":"","Subtema":""},{"Id":"175","Codpais":"VA","Pais":"VATICANO","Anho":"2018","Estatus":"0","Motivo":"","Tmc":"","Subtema":""},{"Id":"176","Codpais":"VA","Pais":"VATICANO","Anho":"2018","Estatus":"0","Motivo":"","Tmc":"","Subtema":""},{"Id":"177","Codpais":"VA","Pais":"VATICANO","Anho":"2018","Estatus":"0","Motivo":"","Tmc":"","Subtema":""},{"Id":"178","Codpais":"VA","Pais":"VATICANO","Anho":"2018","Estatus":"0","Motivo":"","Tmc":"","Subtema":""},{"Id":"179","Codpais":"VA","Pais":"VATICANO","Anho":"2018","Estatus":"0","Motivo":"","Tmc":"","Subtema":""},{"Id":"180","Codpais":"VA","Pais":"VATICANO","Anho":"2018","Estatus":"0","Motivo":"","Tmc":"","Subtema":""},{"Id":"181","Codpais":"VA","Pais":"VATICANO","Anho":"2018","Estatus":"0","Motivo":"","Tmc":"","Subtema":""},{"Id":"182","Codpais":"VA","Pais":"VATICANO","Anho":"2018","Estatus":"0","Motivo":"","Tmc":"","Subtema":""},{"Id":"183","Codpais":"VA","Pais":"VATICANO","Anho":"2018","Estatus":"0","Motivo":"","Tmc":"","Subtema":""},{"Id":"184","Codpais":"VA","Pais":"VATICANO","Anho":"2018","Estatus":"0","Motivo":"","Tmc":"","Subtema":""},{"Id":"185","Codpais":"VA","Pais":"VATICANO","Anho":"2018","Estatus":"0","Motivo":"","Tmc":"","Subtema":""},{"Id":"186","Codpais":"VA","Pais":"VATICANO","Anho":"2018","Estatus":"0","Motivo":"","Tmc":"","Subtema":""},{"Id":"187","Codpais":"VA","Pais":"VATICANO","Anho":"2018","Estatus":"0","Motivo":"","Tmc":"","Subtema":""},{"Id":"188","Codpais":"VA","Pais":"VATICANO","Anho":"2018","Estatus":"0","Motivo":"","Tmc":"","Subtema":""},{"Id":"189","Codpais":"VA","Pais":"VATICANO","Anho":"2018","Estatus":"0","Motivo":"","Tmc":"","Subtema":""},{"Id":"190","Codpais":"VA","Pais":"VATICANO","Anho":"2018","Estatus":"0","Motivo":"","Tmc":"","Subtema":""},{"Id":"191","Codpais":"VA","Pais":"VATICANO","Anho":"2018","Estatus":"0","Motivo":"","Tmc":"","Subtema":""},{"Id":"192","Codpais":"VA","Pais":"VATICANO","Anho":"2018","Estatus":"0","Motivo":"","Tmc":"","Subtema":""},{"Id":"193","Codpais":"VA","Pais":"VATICANO","Anho":"2019","Estatus":"","Motivo":"","Tmc":"","Subtema":""},{"Id":"194","Codpais":"VA","Pais":"VATICANO","Anho":"2019","Estatus":"","Motivo":"","Tmc":"","Subtema":""},{"Id":"195","Codpais":"VA","Pais":"VATICANO","Anho":"2019","Estatus":"","Motivo":"","Tmc":"","Subtema":""},{"Id":"196","Codpais":"VA","Pais":"VATICANO","Anho":"2019","Estatus":"","Motivo":"","Tmc":"","Subtema":""},{"Id":"197","Codpais":"VA","Pais":"VATICANO","Anho":"2019","Estatus":"","Motivo":"","Tmc":"","Subtema":""},{"Id":"198","Codpais":"VA","Pais":"VATICANO","Anho":"2019","Estatus":"","Motivo":"","Tmc":"","Subtema":""},{"Id":"199","Codpais":"VA","Pais":"VATICANO","Anho":"2019","Estatus":"","Motivo":"","Tmc":"","Subtema":""},{"Id":"200","Codpais":"VA","Pais":"VATICANO","Anho":"2019","Estatus":"","Motivo":"","Tmc":"","Subtema":""},{"Id":"201","Codpais":"VA","Pais":"VATICANO","Anho":"2019","Estatus":"","Motivo":"","Tmc":"","Subtema":""},{"Id":"202","Codpais":"VA","Pais":"VATICANO","Anho":"2019","Estatus":"","Motivo":"","Tmc":"","Subtema":""},{"Id":"203","Codpais":"VA","Pais":"VATICANO","Anho":"2019","Estatus":"","Motivo":"","Tmc":"","Subtema":""},{"Id":"204","Codpais":"VA","Pais":"VATICANO","Anho":"2019","Estatus":"","Motivo":"","Tmc":"","Subtema":""},{"Id":"205","Codpais":"VA","Pais":"VATICANO","Anho":"2019","Estatus":"","Motivo":"","Tmc":"","Subtema":""},{"Id":"206","Codpais":"VA","Pais":"VATICANO","Anho":"2019","Estatus":"","Motivo":"","Tmc":"","Subtema":""},{"Id":"207","Codpais":"VA","Pais":"VATICANO","Anho":"2019","Estatus":"","Motivo":"","Tmc":"","Subtema":""},{"Id":"208","Codpais":"VA","Pais":"VATICANO","Anho":"2019","Estatus":"","Motivo":"","Tmc":"","Subtema":""},{"Id":"209","Codpais":"VA","Pais":"VATICANO","Anho":"2019","Estatus":"","Motivo":"","Tmc":"","Subtema":""},{"Id":"210","Codpais":"VA","Pais":"VATICANO","Anho":"2019","Estatus":"","Motivo":"","Tmc":"","Subtema":""},{"Id":"211","Codpais":"VA","Pais":"VATICANO","Anho":"2019","Estatus":"","Motivo":"","Tmc":"","Subtema":""},{"Id":"212","Codpais":"VA","Pais":"VATICANO","Anho":"2019","Estatus":"","Motivo":"","Tmc":"","Subtema":""},{"Id":"213","Codpais":"VA","Pais":"VATICANO","Anho":"2019","Estatus":"","Motivo":"","Tmc":"","Subtema":""},{"Id":"214","Codpais":"VA","Pais":"VATICANO","Anho":"2019","Estatus":"","Motivo":"","Tmc":"","Subtema":""},{"Id":"215","Codpais":"VA","Pais":"VATICANO","Anho":"2019","Estatus":"","Motivo":"","Tmc":"","Subtema":""},{"Id":"216","Codpais":"VA","Pais":"VATICANO","Anho":"2019","Estatus":"","Motivo":"","Tmc":"","Subtema":""},{"Id":"217","Codpais":"VA","Pais":"VATICANO","Anho":"2019","Estatus":"","Motivo":"","Tmc":"","Subtema":""},{"Id":"218","Codpais":"VA","Pais":"VATICANO","Anho":"2019","Estatus":"","Motivo":"","Tmc":"","Subtema":""},{"Id":"219","Codpais":"VA","Pais":"VATICANO","Anho":"2019","Estatus":"","Motivo":"","Tmc":"","Subtema":""},{"Id":"220","Codpais":"VA","Pais":"VATICANO","Anho":"2019","Estatus":"","Motivo":"","Tmc":"","Subtema":""},{"Id":"221","Codpais":"VA","Pais":"VATICANO","Anho":"2019","Estatus":"","Motivo":"","Tmc":"","Subtema":""},{"Id":"222","Codpais":"VA","Pais":"VATICANO","Anho":"2019","Estatus":"","Motivo":"","Tmc":"","Subtema":""},{"Id":"223","Codpais":"VA","Pais":"VATICANO","Anho":"2019","Estatus":"","Motivo":"","Tmc":"","Subtema":""},{"Id":"224","Codpais":"VA","Pais":"VATICANO","Anho":"2019","Estatus":"0","Motivo":"The Annunciation by Pietro Cavallini. Navidad 2019","Tmc":"","Subtema":""},{"Id":"225","Codpais":"VA","Pais":"VATICANO","Anho":"2019","Estatus":"1","Motivo":"The Nativity by Pietro Cavallini. Navidad 2019","Tmc":"","Subtema":""}]}