{"coleccion_IE": [{"Id":"0","Codpais":"IE","Pais":"IRLANDA","Anho":"1997","Estatus":"1","Motivo":"Drácula","Tmc":"ARTE","Subtema":"Literatura"},{"Id":"1","Codpais":"IE","Pais":"IRLANDA","Anho":"1997","Estatus":"1","Motivo":"Drácula","Tmc":"ARTE","Subtema":"Literatura"},{"Id":"2","Codpais":"IE","Pais":"IRLANDA","Anho":"2016","Estatus":"1","Motivo":"Roger Casement","Tmc":"","Subtema":""},{"Id":"3","Codpais":"IE","Pais":"IRLANDA","Anho":"1971","Estatus":"0","Motivo":"J M Synge 1871-1909","Tmc":"CINE","Subtema":""},{"Id":"4","Codpais":"IE","Pais":"IRLANDA","Anho":"1971","Estatus":"0","Motivo":"J M Synge 1871-1909","Tmc":"CINE","Subtema":""},{"Id":"5","Codpais":"IE","Pais":"IRLANDA","Anho":"2009","Estatus":"0","Motivo":"Death centenary of John Millington Synge, playwright","Tmc":"CINE","Subtema":""},{"Id":"6","Codpais":"IE","Pais":"IRLANDA","Anho":"2004","Estatus":"1","Motivo":"Centenary of Leopold Bloom's Adventure (from Ulysses). Joyce","Tmc":"","Subtema":""},{"Id":"7","Codpais":"IE","Pais":"IRLANDA","Anho":"1965","Estatus":"1","Motivo":"William Butler Yeats (1865-1939)","Tmc":"","Subtema":""},{"Id":"8","Codpais":"IE","Pais":"IRLANDA","Anho":"1966","Estatus":"1","Motivo":"Roger Casement (1864-1916)","Tmc":"","Subtema":""},{"Id":"9","Codpais":"IE","Pais":"IRLANDA","Anho":"2018","Estatus":"1","Motivo":"Visita del Papa Francisco a Irlanda","Tmc":"","Subtema":""},{"Id":"10","Codpais":"IE","Pais":"IRLANDA","Anho":"2018","Estatus":"1","Motivo":"Visita del Papa Francisco a Irlanda","Tmc":"","Subtema":""}]}