{"subTematicas": [{"Tmc":"HISTORIA","Subtema":"Batallas"},{"Tmc":"Gente","Subtema":"Poeta"},{"Tmc":"ARTE","Subtema":"Rom\u00E1nico"},{"Tmc":"Gente","Subtema":"Te\u00F3logo"},{"Tmc":"HISTORIA","Subtema":"Imperio Romano"},{"Tmc":"Literatura infantil","Subtema":"Fairy tale"},{"Tmc":"Literatura infantil","Subtema":"Dibujos animados"},{"Tmc":"LITERATURA","Subtema":"Literatura"},{"Tmc":"ARTE","Subtema":"Pintura"},{"Tmc":"Arte","Subtema":"Escultura"},{"Tmc":"Arte","Subtema":"Literatura"},{"Tmc":"Gente","Subtema":"Arte"},{"Tmc":"ARTE","Subtema":"Arquitectura"},{"Tmc":"Arte","Subtema":"Pintura"},{"Tmc":"Gente","Subtema":"Filosof\u00EDa"},{"Tmc":"ARTE","Subtema":"Modernismo"},{"Tmc":"ARTE","Subtema":"Modernismo y Mitolog\u00EDa"},{"Tmc":"ARTE","Subtema":"Escultura"},{"Tmc":"Literatura infantil","Subtema":"Ilustradores"},{"Tmc":"Arte","Subtema":"M\u00FAsica"},{"Tmc":"Arte","Subtema":"Literatura infantil"},{"Tmc":"ARTE","Subtema":"ARQUITECTURA"},{"Tmc":"Arte","Subtema":"Arquitectura"},{"Tmc":"CINE","Subtema":"Hollywood"},{"Tmc":"Turismo","Subtema":"Fuentes"},{"Tmc":"Turismo-Ciudades-Excursiones","Subtema":"Barcelona"},{"Tmc":"Gente","Subtema":"Fil\u00F3sofo, te\u00F3logo y Jurista"},{"Tmc":"ARTE","Subtema":"Decoraci\u00F3n"},{"Tmc":"Literatura infantil","Subtema":"Comics"},{"Tmc":"Gente","Subtema":"Compositor"},{"Tmc":"LITERATURA","Subtema":"Escritores conv"},{"Tmc":"Gente","Subtema":"Pintor"},{"Tmc":"Gente","Subtema":"Literatura"},{"Tmc":"ARTE","Subtema":"Literatura"},{"Tmc":"ARTE","Subtema":"Textiles"},{"Tmc":"Arte","Subtema":" Pintura"},{"Tmc":"ARTE","Subtema":"Cine"},{"Tmc":"ARTE","Subtema":"Literarura"},{"Tmc":"Arte","Subtema":"Graffiti"},{"Tmc":"ARTE","Subtema":"Escritores"},{"Tmc":"Arte","Subtema":"Pop Art"},{"Tmc":"Arte","Subtema":"Pop art"},{"Tmc":"Ciencia","Subtema":"F\u00EDsica"},{"Tmc":"Arte","Subtema":"Textiles"},{"Tmc":"Gente","Subtema":"Ciencia"},{"Tmc":"ARTE","Subtema":"Miguel \u00C1ngel"},{"Tmc":"ARTE","Subtema":"Capilla Sixtina"},{"Tmc":"ARTE","Subtema":"P\u00EEntura"},{"Tmc":"OTRAS","Subtema":"COCHES"},{"Tmc":"OTRAS","Subtema":"MONEDAS"},{"Tmc":"OTRAS","Subtema":"Moda"},{"Tmc":"Gente","Subtema":"F\u00EDsica"},{"Tmc":"Literatura infantil","Subtema":"Manga"},{"Tmc":"Literatura infantil","Subtema":"Anime"},{"Tmc":"ARTE","Subtema":"Muralistas"},{"Tmc":"Gente","Subtema":"Filosof\u00EDa-Teolog\u00EDa"},{"Tmc":"OTRAS","Subtema":"Perros"},{"Tmc":"ARTE","Subtema":"Surrealismo"},{"Tmc":"Literatura infantil","Subtema":"Cuentos"},{"Tmc":"Literatura infantil","Subtema":"Fairy tales"},{"Tmc":"Gente","Subtema":"Gigantes de la industria"},{"Tmc":"Literatura infantil","Subtema":"Animae"},{"Tmc":"ARTE","Subtema":"Fotograf\u00EDa"},{"Tmc":"Gente","Subtema":"Historia"},{"Tmc":"ARTE","Subtema":"Bauhaus"},{"Tmc":"OTRAS","Subtema":"F\u00FAtbol"},{"Tmc":"Arte","Subtema":"Simbolismo"},{"Tmc":"Arte","Subtema":"Modernismo"},{"Tmc":"Arte","Subtema":"Surrealismo"}]}